nb_cell_tools/static/index.js
nb_cell_tools/static/jquery.dialogextend.js
nb_cell_tools/static/nb_cell_tools.png
nb_cell_tools/static/nb_cell_tools.yaml
nbev3devsim/__init__.py
nbev3devsim/ev3devsim_nb.py
nbev3devsim/load_nbev3devwidget.py
nbev3devsim/magics.py
nbev3devsim/tqdma.py
nbev3devsim/backgrounds/FLL2018.jpg
nbev3devsim/backgrounds/FLL2019.jpg
nbev3devsim/backgrounds/FuBK_testcard_vectorized.png
nbev3devsim/backgrounds/Junction_Handling_Test.png
nbev3devsim/backgrounds/Line_Following_Test.png
nbev3devsim/backgrounds/Logo.svg
nbev3devsim/backgrounds/Obstacles_Test.png
nbev3devsim/backgrounds/Topo_map.png
nbev3devsim/backgrounds/WRO-2018-Regular-Junior.png
nbev3devsim/backgrounds/WRO-2019-Regular-Junior.jpg
nbev3devsim/backgrounds/WRO-2019-Regular-Junior.png
nbev3devsim/backgrounds/_blank.png
nbev3devsim/backgrounds/_coloured_bands.png
nbev3devsim/backgrounds/_grey_and_black.png
nbev3devsim/backgrounds/_greys.png
nbev3devsim/backgrounds/_line_follower_track.png
nbev3devsim/backgrounds/_linear_grey.png
nbev3devsim/backgrounds/_loop.png
nbev3devsim/backgrounds/_noisy_line_follower_track.png
nbev3devsim/backgrounds/_number_sheet.png
nbev3devsim/backgrounds/_number_sheet_black.png
nbev3devsim/backgrounds/_radial_grey.png
nbev3devsim/backgrounds/_radial_red.png
nbev3devsim/backgrounds/_rainbow_bands.png
nbev3devsim/backgrounds/_regular_shapes.png
nbev3devsim/backgrounds/_sensor_diameter_test.png
nbev3devsim/backgrounds/_simple_shapes.png
nbev3devsim/backgrounds/_square.png
nbev3devsim/backgrounds/_two_shapes.png
nbev3devsim/backgrounds/junction_test.svg
nbev3devsim/backgrounds/line_test.svg
nbev3devsim/backgrounds/obstacles_test.svg
nbev3devsim/backgrounds/thruxton_track.png
nbev3devsim/css/main.css
nbev3devsim/js/EV3devSim.js
nbev3devsim/js/ev3dev2_glue.js
nbev3devsim/js/jquery.dialogextend.js
nbev3devsim/js/plotly.min.js
nbev3devsim/js/prism.js
nbev3devsim/js/skulpt-stdlib.js
nbev3devsim/js/skulpt.min.js
nbev3devsim/progs/prog1.py
nbev3devsim-0.0.12.dist-info/LICENSE
nbev3devsim-0.0.12.dist-info/METADATA
nbev3devsim-0.0.12.dist-info/WHEEL
nbev3devsim-0.0.12.dist-info/top_level.txt
nbev3devsim-0.0.12.dist-info/RECORD
