Metadata-Version: 2.1
Name: nbev3devsim
Version: 0.0.12
Summary: nbevdevsim - ev3devsim extension for Jupyter notebooks
Home-page: https://github.com/innovationOUtside/innovationOUtside/nbev3devsim
Author: Tony Hirst
Author-email: tony.hirst@open.ac.uk
License: MIT License
Platform: UNKNOWN
License-File: LICENSE
Requires-Dist: jp-proxy-widget
Requires-Dist: nest-asyncio
Requires-Dist: pandas
Requires-Dist: seaborn
Requires-Dist: tqdm
Requires-Dist: nb-extension-empinken
Requires-Dist: scikit-learn
